AUTHORS
CHANGELOG.rst
LICENSE
MANIFEST.in
README
README.rst
requirements.txt
setup.cfg
setup.py
docs/CHANGELOG.rst
docs/CONTRIBUTING.rst
docs/LICENSE.rst
docs/README.rst
docs/conf.py
docs/index.rst
docs/html/index.html
modint/__init__.py
modint/__main__.py
modint/cli.py
modint/template.py
modint.egg-info/PKG-INFO
modint.egg-info/SOURCES.txt
modint.egg-info/dependency_links.txt
modint.egg-info/not-zip-safe
modint.egg-info/top_level.txt
tests/__init__.py
tests/test_modint.py
tests/test_sanity.py